{
    "format_version": "1.8.0",
    "minecraft:entity": {
        "components": {
            "badger:buildable_presentation": {
                "buildable_category": "utility",
                "icon": "utility",
                "sort_order": 10287,
                "tactical_description": "zoner_piglin_obstacle_territory_foundation",
                "tooltip_description": "zoner_piglin_obstacle_territory_foundation",
                "tooltip_title": "zoner_piglin_obstacle_territory_foundation"
            },
            "badger:buildable_requirement": {
                "invalid_block_tags": [],
                "invalid_blocks": []
            },
            "badger:buildable_structure": {
                "build_time": 0,
                "construction_end_trigger": "on_construction_end",
                "construction_start_trigger": "on_construction_start",
                "nbt_file": "zoner_piglin_obstacle_territory_foundation"
            },
            "badger:tags": {
                "tags": [
                    "zoner_piglin_obstacle_territory_foundation"
                ]
            },
            "badger:template": [
                "badger:template_structure"
            ]
        },
        "description": {
            "identifier": "accessible_architecture:zoner_piglin_obstacle_territory_foundation",
            "is_summonable": true,
            "runtime_identifier": "badger:buildable"
        },
        "mushroom_data": {
            "function": "Military",
            "type": "Piglin"
        }
    }
}